	.text
	.file	"lopcodes.c"
	.type	.L.str,@object          # @.str
	.section	.rodata.str1.1,"aMS",@progbits,1
.L.str:
	.asciz	"MOVE"
	.size	.L.str, 5

	.type	.L.str.1,@object        # @.str.1
.L.str.1:
	.asciz	"LOADK"
	.size	.L.str.1, 6

	.type	.L.str.2,@object        # @.str.2
.L.str.2:
	.asciz	"LOADBOOL"
	.size	.L.str.2, 9

	.type	.L.str.3,@object        # @.str.3
.L.str.3:
	.asciz	"LOADNIL"
	.size	.L.str.3, 8

	.type	.L.str.4,@object        # @.str.4
.L.str.4:
	.asciz	"GETUPVAL"
	.size	.L.str.4, 9

	.type	.L.str.5,@object        # @.str.5
.L.str.5:
	.asciz	"GETGLOBAL"
	.size	.L.str.5, 10

	.type	.L.str.6,@object        # @.str.6
.L.str.6:
	.asciz	"GETTABLE"
	.size	.L.str.6, 9

	.type	.L.str.7,@object        # @.str.7
.L.str.7:
	.asciz	"SETGLOBAL"
	.size	.L.str.7, 10

	.type	.L.str.8,@object        # @.str.8
.L.str.8:
	.asciz	"SETUPVAL"
	.size	.L.str.8, 9

	.type	.L.str.9,@object        # @.str.9
.L.str.9:
	.asciz	"SETTABLE"
	.size	.L.str.9, 9

	.type	.L.str.10,@object       # @.str.10
.L.str.10:
	.asciz	"NEWTABLE"
	.size	.L.str.10, 9

	.type	.L.str.11,@object       # @.str.11
.L.str.11:
	.asciz	"SELF"
	.size	.L.str.11, 5

	.type	.L.str.12,@object       # @.str.12
.L.str.12:
	.asciz	"ADD"
	.size	.L.str.12, 4

	.type	.L.str.13,@object       # @.str.13
.L.str.13:
	.asciz	"SUB"
	.size	.L.str.13, 4

	.type	.L.str.14,@object       # @.str.14
.L.str.14:
	.asciz	"MUL"
	.size	.L.str.14, 4

	.type	.L.str.15,@object       # @.str.15
.L.str.15:
	.asciz	"DIV"
	.size	.L.str.15, 4

	.type	.L.str.16,@object       # @.str.16
.L.str.16:
	.asciz	"MOD"
	.size	.L.str.16, 4

	.type	.L.str.17,@object       # @.str.17
.L.str.17:
	.asciz	"POW"
	.size	.L.str.17, 4

	.type	.L.str.18,@object       # @.str.18
.L.str.18:
	.asciz	"UNM"
	.size	.L.str.18, 4

	.type	.L.str.19,@object       # @.str.19
.L.str.19:
	.asciz	"NOT"
	.size	.L.str.19, 4

	.type	.L.str.20,@object       # @.str.20
.L.str.20:
	.asciz	"LEN"
	.size	.L.str.20, 4

	.type	.L.str.21,@object       # @.str.21
.L.str.21:
	.asciz	"CONCAT"
	.size	.L.str.21, 7

	.type	.L.str.22,@object       # @.str.22
.L.str.22:
	.asciz	"JMP"
	.size	.L.str.22, 4

	.type	.L.str.23,@object       # @.str.23
.L.str.23:
	.asciz	"EQ"
	.size	.L.str.23, 3

	.type	.L.str.24,@object       # @.str.24
.L.str.24:
	.asciz	"LT"
	.size	.L.str.24, 3

	.type	.L.str.25,@object       # @.str.25
.L.str.25:
	.asciz	"LE"
	.size	.L.str.25, 3

	.type	.L.str.26,@object       # @.str.26
.L.str.26:
	.asciz	"TEST"
	.size	.L.str.26, 5

	.type	.L.str.27,@object       # @.str.27
.L.str.27:
	.asciz	"TESTSET"
	.size	.L.str.27, 8

	.type	.L.str.28,@object       # @.str.28
.L.str.28:
	.asciz	"CALL"
	.size	.L.str.28, 5

	.type	.L.str.29,@object       # @.str.29
.L.str.29:
	.asciz	"TAILCALL"
	.size	.L.str.29, 9

	.type	.L.str.30,@object       # @.str.30
.L.str.30:
	.asciz	"RETURN"
	.size	.L.str.30, 7

	.type	.L.str.31,@object       # @.str.31
.L.str.31:
	.asciz	"FORLOOP"
	.size	.L.str.31, 8

	.type	.L.str.32,@object       # @.str.32
.L.str.32:
	.asciz	"FORPREP"
	.size	.L.str.32, 8

	.type	.L.str.33,@object       # @.str.33
.L.str.33:
	.asciz	"TFORLOOP"
	.size	.L.str.33, 9

	.type	.L.str.34,@object       # @.str.34
.L.str.34:
	.asciz	"SETLIST"
	.size	.L.str.34, 8

	.type	.L.str.35,@object       # @.str.35
.L.str.35:
	.asciz	"CLOSE"
	.size	.L.str.35, 6

	.type	.L.str.36,@object       # @.str.36
.L.str.36:
	.asciz	"CLOSURE"
	.size	.L.str.36, 8

	.type	.L.str.37,@object       # @.str.37
.L.str.37:
	.asciz	"VARARG"
	.size	.L.str.37, 7

	.hidden	luaP_opnames            # @luaP_opnames
	.type	luaP_opnames,@object
	.section	.rodata,"a",@progbits
	.globl	luaP_opnames
	.p2align	4
luaP_opnames:
	.quad	.L.str
	.quad	.L.str.1
	.quad	.L.str.2
	.quad	.L.str.3
	.quad	.L.str.4
	.quad	.L.str.5
	.quad	.L.str.6
	.quad	.L.str.7
	.quad	.L.str.8
	.quad	.L.str.9
	.quad	.L.str.10
	.quad	.L.str.11
	.quad	.L.str.12
	.quad	.L.str.13
	.quad	.L.str.14
	.quad	.L.str.15
	.quad	.L.str.16
	.quad	.L.str.17
	.quad	.L.str.18
	.quad	.L.str.19
	.quad	.L.str.20
	.quad	.L.str.21
	.quad	.L.str.22
	.quad	.L.str.23
	.quad	.L.str.24
	.quad	.L.str.25
	.quad	.L.str.26
	.quad	.L.str.27
	.quad	.L.str.28
	.quad	.L.str.29
	.quad	.L.str.30
	.quad	.L.str.31
	.quad	.L.str.32
	.quad	.L.str.33
	.quad	.L.str.34
	.quad	.L.str.35
	.quad	.L.str.36
	.quad	.L.str.37
	.quad	0
	.size	luaP_opnames, 312

	.hidden	luaP_opmodes            # @luaP_opmodes
	.type	luaP_opmodes,@object
	.globl	luaP_opmodes
	.p2align	4
luaP_opmodes:
	.ascii	"`qT`Pql1\020<Tl||||||```h\"\274\274\274\344\344TT\020bb\204\024\000QP"
	.size	luaP_opmodes, 38

	.ident	"clang version 7.0.1-8+deb10u2 (tags/RELEASE_701/final)"
	.section	".note.GNU-stack","",@progbits
