; ModuleID = '/root/.unikraft/apps/redis/build/libredis/origin/redis-5.0.6/deps/lua/src/lopcodes.c'
source_filename = "/root/.unikraft/apps/redis/build/libredis/origin/redis-5.0.6/deps/lua/src/lopcodes.c"
target datalayout = "e-m:e-i64:64-f80:128-n8:16:32:64-S128"
target triple = "x86_64-pc-linux-gnu"

@.str = private unnamed_addr constant [5 x i8] c"MOVE\00", align 1
@.str.1 = private unnamed_addr constant [6 x i8] c"LOADK\00", align 1
@.str.2 = private unnamed_addr constant [9 x i8] c"LOADBOOL\00", align 1
@.str.3 = private unnamed_addr constant [8 x i8] c"LOADNIL\00", align 1
@.str.4 = private unnamed_addr constant [9 x i8] c"GETUPVAL\00", align 1
@.str.5 = private unnamed_addr constant [10 x i8] c"GETGLOBAL\00", align 1
@.str.6 = private unnamed_addr constant [9 x i8] c"GETTABLE\00", align 1
@.str.7 = private unnamed_addr constant [10 x i8] c"SETGLOBAL\00", align 1
@.str.8 = private unnamed_addr constant [9 x i8] c"SETUPVAL\00", align 1
@.str.9 = private unnamed_addr constant [9 x i8] c"SETTABLE\00", align 1
@.str.10 = private unnamed_addr constant [9 x i8] c"NEWTABLE\00", align 1
@.str.11 = private unnamed_addr constant [5 x i8] c"SELF\00", align 1
@.str.12 = private unnamed_addr constant [4 x i8] c"ADD\00", align 1
@.str.13 = private unnamed_addr constant [4 x i8] c"SUB\00", align 1
@.str.14 = private unnamed_addr constant [4 x i8] c"MUL\00", align 1
@.str.15 = private unnamed_addr constant [4 x i8] c"DIV\00", align 1
@.str.16 = private unnamed_addr constant [4 x i8] c"MOD\00", align 1
@.str.17 = private unnamed_addr constant [4 x i8] c"POW\00", align 1
@.str.18 = private unnamed_addr constant [4 x i8] c"UNM\00", align 1
@.str.19 = private unnamed_addr constant [4 x i8] c"NOT\00", align 1
@.str.20 = private unnamed_addr constant [4 x i8] c"LEN\00", align 1
@.str.21 = private unnamed_addr constant [7 x i8] c"CONCAT\00", align 1
@.str.22 = private unnamed_addr constant [4 x i8] c"JMP\00", align 1
@.str.23 = private unnamed_addr constant [3 x i8] c"EQ\00", align 1
@.str.24 = private unnamed_addr constant [3 x i8] c"LT\00", align 1
@.str.25 = private unnamed_addr constant [3 x i8] c"LE\00", align 1
@.str.26 = private unnamed_addr constant [5 x i8] c"TEST\00", align 1
@.str.27 = private unnamed_addr constant [8 x i8] c"TESTSET\00", align 1
@.str.28 = private unnamed_addr constant [5 x i8] c"CALL\00", align 1
@.str.29 = private unnamed_addr constant [9 x i8] c"TAILCALL\00", align 1
@.str.30 = private unnamed_addr constant [7 x i8] c"RETURN\00", align 1
@.str.31 = private unnamed_addr constant [8 x i8] c"FORLOOP\00", align 1
@.str.32 = private unnamed_addr constant [8 x i8] c"FORPREP\00", align 1
@.str.33 = private unnamed_addr constant [9 x i8] c"TFORLOOP\00", align 1
@.str.34 = private unnamed_addr constant [8 x i8] c"SETLIST\00", align 1
@.str.35 = private unnamed_addr constant [6 x i8] c"CLOSE\00", align 1
@.str.36 = private unnamed_addr constant [8 x i8] c"CLOSURE\00", align 1
@.str.37 = private unnamed_addr constant [7 x i8] c"VARARG\00", align 1
@luaP_opnames = hidden local_unnamed_addr constant [39 x i8*] [i8* getelementptr inbounds ([5 x i8], [5 x i8]* @.str, i32 0, i32 0), i8* getelementptr inbounds ([6 x i8], [6 x i8]* @.str.1, i32 0, i32 0), i8* getelementptr inbounds ([9 x i8], [9 x i8]* @.str.2, i32 0, i32 0), i8* getelementptr inbounds ([8 x i8], [8 x i8]* @.str.3, i32 0, i32 0), i8* getelementptr inbounds ([9 x i8], [9 x i8]* @.str.4, i32 0, i32 0), i8* getelementptr inbounds ([10 x i8], [10 x i8]* @.str.5, i32 0, i32 0), i8* getelementptr inbounds ([9 x i8], [9 x i8]* @.str.6, i32 0, i32 0), i8* getelementptr inbounds ([10 x i8], [10 x i8]* @.str.7, i32 0, i32 0), i8* getelementptr inbounds ([9 x i8], [9 x i8]* @.str.8, i32 0, i32 0), i8* getelementptr inbounds ([9 x i8], [9 x i8]* @.str.9, i32 0, i32 0), i8* getelementptr inbounds ([9 x i8], [9 x i8]* @.str.10, i32 0, i32 0), i8* getelementptr inbounds ([5 x i8], [5 x i8]* @.str.11, i32 0, i32 0), i8* getelementptr inbounds ([4 x i8], [4 x i8]* @.str.12, i32 0, i32 0), i8* getelementptr inbounds ([4 x i8], [4 x i8]* @.str.13, i32 0, i32 0), i8* getelementptr inbounds ([4 x i8], [4 x i8]* @.str.14, i32 0, i32 0), i8* getelementptr inbounds ([4 x i8], [4 x i8]* @.str.15, i32 0, i32 0), i8* getelementptr inbounds ([4 x i8], [4 x i8]* @.str.16, i32 0, i32 0), i8* getelementptr inbounds ([4 x i8], [4 x i8]* @.str.17, i32 0, i32 0), i8* getelementptr inbounds ([4 x i8], [4 x i8]* @.str.18, i32 0, i32 0), i8* getelementptr inbounds ([4 x i8], [4 x i8]* @.str.19, i32 0, i32 0), i8* getelementptr inbounds ([4 x i8], [4 x i8]* @.str.20, i32 0, i32 0), i8* getelementptr inbounds ([7 x i8], [7 x i8]* @.str.21, i32 0, i32 0), i8* getelementptr inbounds ([4 x i8], [4 x i8]* @.str.22, i32 0, i32 0), i8* getelementptr inbounds ([3 x i8], [3 x i8]* @.str.23, i32 0, i32 0), i8* getelementptr inbounds ([3 x i8], [3 x i8]* @.str.24, i32 0, i32 0), i8* getelementptr inbounds ([3 x i8], [3 x i8]* @.str.25, i32 0, i32 0), i8* getelementptr inbounds ([5 x i8], [5 x i8]* @.str.26, i32 0, i32 0), i8* getelementptr inbounds ([8 x i8], [8 x i8]* @.str.27, i32 0, i32 0), i8* getelementptr inbounds ([5 x i8], [5 x i8]* @.str.28, i32 0, i32 0), i8* getelementptr inbounds ([9 x i8], [9 x i8]* @.str.29, i32 0, i32 0), i8* getelementptr inbounds ([7 x i8], [7 x i8]* @.str.30, i32 0, i32 0), i8* getelementptr inbounds ([8 x i8], [8 x i8]* @.str.31, i32 0, i32 0), i8* getelementptr inbounds ([8 x i8], [8 x i8]* @.str.32, i32 0, i32 0), i8* getelementptr inbounds ([9 x i8], [9 x i8]* @.str.33, i32 0, i32 0), i8* getelementptr inbounds ([8 x i8], [8 x i8]* @.str.34, i32 0, i32 0), i8* getelementptr inbounds ([6 x i8], [6 x i8]* @.str.35, i32 0, i32 0), i8* getelementptr inbounds ([8 x i8], [8 x i8]* @.str.36, i32 0, i32 0), i8* getelementptr inbounds ([7 x i8], [7 x i8]* @.str.37, i32 0, i32 0), i8* null], align 16, !dbg !0
@luaP_opmodes = hidden local_unnamed_addr constant [38 x i8] c"`qT`Pql1\10<Tl||||||```h\22\BC\BC\BC\E4\E4TT\10bb\84\14\00QP", align 16, !dbg !6

!llvm.dbg.cu = !{!2}
!llvm.module.flags = !{!22, !23, !24}
!llvm.ident = !{!25}

!0 = !DIGlobalVariableExpression(var: !1, expr: !DIExpression())
!1 = distinct !DIGlobalVariable(name: "luaP_opnames", scope: !2, file: !3, line: 16, type: !15, isLocal: false, isDefinition: true)
!2 = distinct !DICompileUnit(language: DW_LANG_C99, file: !3, producer: "clang version 7.0.1-8+deb10u2 (tags/RELEASE_701/final)", isOptimized: true, runtimeVersion: 0, emissionKind: FullDebug, enums: !4, globals: !5)
!3 = !DIFile(filename: "/root/.unikraft/apps/redis/build/libredis/origin/redis-5.0.6/deps/lua/src/lopcodes.c", directory: "/root/.unikraft/apps/redis/build")
!4 = !{}
!5 = !{!0, !6}
!6 = !DIGlobalVariableExpression(var: !7, expr: !DIExpression())
!7 = distinct !DIGlobalVariable(name: "luaP_opmodes", scope: !2, file: !3, line: 61, type: !8, isLocal: false, isDefinition: true)
!8 = !DICompositeType(tag: DW_TAG_array_type, baseType: !9, size: 304, elements: !13)
!9 = !DIDerivedType(tag: DW_TAG_const_type, baseType: !10)
!10 = !DIDerivedType(tag: DW_TAG_typedef, name: "lu_byte", file: !11, line: 27, baseType: !12)
!11 = !DIFile(filename: "/root/.unikraft/apps/redis/build/libredis/origin/redis-5.0.6/deps/lua/src/llimits.h", directory: "/root/.unikraft/apps/redis/build")
!12 = !DIBasicType(name: "unsigned char", size: 8, encoding: DW_ATE_unsigned_char)
!13 = !{!14}
!14 = !DISubrange(count: 38)
!15 = !DICompositeType(tag: DW_TAG_array_type, baseType: !16, size: 2496, elements: !20)
!16 = !DIDerivedType(tag: DW_TAG_const_type, baseType: !17)
!17 = !DIDerivedType(tag: DW_TAG_pointer_type, baseType: !18, size: 64)
!18 = !DIDerivedType(tag: DW_TAG_const_type, baseType: !19)
!19 = !DIBasicType(name: "char", size: 8, encoding: DW_ATE_signed_char)
!20 = !{!21}
!21 = !DISubrange(count: 39)
!22 = !{i32 2, !"Dwarf Version", i32 4}
!23 = !{i32 2, !"Debug Info Version", i32 3}
!24 = !{i32 1, !"wchar_size", i32 4}
!25 = !{!"clang version 7.0.1-8+deb10u2 (tags/RELEASE_701/final)"}
